asyncnewsapi/__init__.py
asyncnewsapi/auth.py
asyncnewsapi/session.py
asyncnewsapi/stream.py
asyncnewsapi-0.2.1.dist-info/LICENSE
asyncnewsapi-0.2.1.dist-info/METADATA
asyncnewsapi-0.2.1.dist-info/WHEEL
asyncnewsapi-0.2.1.dist-info/top_level.txt
asyncnewsapi-0.2.1.dist-info/RECORD
