Metadata-Version: 2.1
Name: asyncnewsapi
Version: 0.2.1
Summary: AsyncIO Python wrapper to News API
Home-page: https://github.com/pkpinto/asyncnewsapi
Author: Paulo Kauscher Pinto
Author-email: paulo.kauscher.pinto@icloud.com
License: Apache License 2.0
Platform: UNKNOWN
Classifier: Development Status :: 4 - Beta
Classifier: License :: OSI Approved :: Apache Software License
Classifier: Programming Language :: Python :: 3.7
Classifier: Topic :: Software Development :: Libraries :: Python Modules
Classifier: Intended Audience :: Developers
Requires-Dist: aiohttp (<4,>=3.5)
Requires-Dist: async-timeout
Requires-Dist: yarl
Provides-Extra: test
Requires-Dist: pytest (<5.3) ; extra == 'test'
Requires-Dist: pytest-cov ; extra == 'test'
Requires-Dist: aiohttp (<4,>=3.5) ; extra == 'test'
Requires-Dist: async-timeout ; extra == 'test'
Requires-Dist: yarl ; extra == 'test'
